cambd/__init__.py
cambd/__main__.py
cambd/cache.py
cambd/cambd.py
cambd-1.0.2.dist-info/LICENSE
cambd-1.0.2.dist-info/METADATA
cambd-1.0.2.dist-info/WHEEL
cambd-1.0.2.dist-info/entry_points.txt
cambd-1.0.2.dist-info/top_level.txt
cambd-1.0.2.dist-info/RECORD
