Metadata-Version: 2.1
Name: cambd
Version: 1.0.2
Summary: Cambridge dictionary cli app
Home-page: https://github.com/rocktimsaikia/cambd
Author: Rocktim Saikia
Author-email: saikia.rocktim@proton.me
License: MIT
Classifier: Environment :: Console
Classifier: Development Status :: 5 - Production/Stable
Classifier: Programming Language :: Python :: 3
Classifier: Programming Language :: Python :: 3.7
Classifier: Programming Language :: Python :: 3.8
Classifier: Programming Language :: Python :: 3.9
Classifier: Programming Language :: Python :: 3.10
Classifier: License :: OSI Approved :: MIT License
Classifier: Operating System :: OS Independent
Classifier: Topic :: Terminals
Classifier: Topic :: Utilities
License-File: LICENSE
Requires-Dist: beautifulsoup4 >=4.11.1
Requires-Dist: html5lib >=1.1.0
Requires-Dist: click >=8.0.3
Requires-Dist: halo >=0.0.31
Requires-Dist: requests >=2.25.1
Requires-Dist: rich >=12.6.0
Requires-Dist: simple-term-menu >=1.5.2
